porous_media/__init__.py
porous_media/console.py
porous_media/log.py
porous_media/py.typed
porous_media/analyses/__init__.py
porous_media/analyses/liver_variables.py
porous_media/analyses/examples/__init__.py
porous_media/analyses/examples/groups.py
porous_media/analyses/simliva/__init__.py
porous_media/analyses/simliva/simliva_example.py
porous_media/analyses/spt/MII-symposium.md
porous_media/analyses/spt/__init__.py
porous_media/analyses/spt/spt.md
porous_media/analyses/spt/spt_data_processing.py
porous_media/analyses/spt/spt_information.py
porous_media/analyses/spt/spt_plots_analysis.py
porous_media/analyses/spt/spt_plots_geometry.py
porous_media/data/__init__.py
porous_media/data/flow_dependency.png
porous_media/data/xdmf_calculations.py
porous_media/data/xdmf_tools.py
porous_media/febio/__init__.py
porous_media/febio/febio_manipulation.py
porous_media/mesh/__init__.py
porous_media/mesh/mesh_tools.py
porous_media/mesh/mesh_zonation.py
porous_media/resources/images/mesh_zonation.png
porous_media/resources/vtk/vtk_single/lobule_zonation_pattern.t0022.vtk
porous_media/resources/vtk/vtk_timecourse/lobule_zonation_pattern.t0000.vtk
porous_media/resources/vtk/vtk_timecourse/lobule_zonation_pattern.t0008.vtk
porous_media/resources/vtk/vtk_timecourse/lobule_zonation_pattern.t0022.vtk
porous_media/resources/zonation/mesh_zonation.h5
porous_media/resources/zonation/mesh_zonation.vtk
porous_media/resources/zonation/mesh_zonation.xdmf
porous_media/resources/zonation/mesh_zonation_lobulus.vtk
porous_media/visualization/__init__.py
porous_media/visualization/image_annotation.py
porous_media/visualization/image_manipulation.py
porous_media/visualization/plots.py
porous_media/visualization/pyvista_visualization.py
porous_media/visualization/video.py
porous_media/visualization/vtu_reader.py
porous_media-0.2.2.dist-info/LICENSE
porous_media-0.2.2.dist-info/METADATA
porous_media-0.2.2.dist-info/WHEEL
porous_media-0.2.2.dist-info/top_level.txt
porous_media-0.2.2.dist-info/zip-safe
porous_media-0.2.2.dist-info/RECORD
