Metadata-Version: 2.1
Name: porous_media
Version: 0.2.2
Summary: python package working with porous media
Home-page: https://github.com/matthiaskoenig/porous_media
Download-URL: https://pypi.org/project/porous_media
Author: Matthias Koenig
Author-email: konigmatt@googlemail.com
Maintainer: Matthias Koenig
Maintainer-email: konigmatt@googlemail.com
License: LGPL-3.0
Project-URL: Source Code, https://github.com/matthiaskoenig/porous_media
Project-URL: Documentation, https://github.com/matthiaskoenig/porous_media
Project-URL: Bug Tracker, https://github.com/matthiaskoenig/porous_media/issues
Keywords: porous media
Classifier: Development Status :: 4 - Beta
Classifier: Intended Audience :: Science/Research
Classifier: License :: OSI Approved :: GNU Lesser General Public License v3 (LGPLv3)
Classifier: Operating System :: OS Independent
Classifier: Programming Language :: Python :: 3.9
Classifier: Programming Language :: Python :: 3.10
Classifier: Programming Language :: Python :: 3.11
Classifier: Programming Language :: Python :: 3.12
Classifier: Programming Language :: Python :: Implementation :: CPython
Classifier: Topic :: Scientific/Engineering
Classifier: Topic :: Scientific/Engineering :: Bio-Informatics
Requires-Python: >=3.9
License-File: LICENSE
Requires-Dist: pandas >=2.0.3
Requires-Dist: xarray >=2023.8.0
Requires-Dist: openpyxl >=3.1.2
Requires-Dist: rich >=13.4.2
Requires-Dist: meshio >=5.3.5
Requires-Dist: meshplex >=0.19.1
Requires-Dist: pyvista >=0.43.2
Requires-Dist: scipy >=1.11.1
Requires-Dist: dataclasses-json >=0.6.0
Requires-Dist: jinja2 >=3.1.2
Requires-Dist: Pillow >=10.0.0
Requires-Dist: h5py >=3.9
Provides-Extra: development
Requires-Dist: pip-tools >6.10 ; extra == 'development'
Requires-Dist: black >=24.1.1 ; extra == 'development'
Requires-Dist: bump2version >=1.0.1 ; extra == 'development'
Requires-Dist: isort >=5.13.2 ; extra == 'development'
Requires-Dist: tox >=4.12.1 ; extra == 'development'
Requires-Dist: flake8 >=6.1.0 ; extra == 'development'
Requires-Dist: flake8-mypy >=17.8.0 ; extra == 'development'
Requires-Dist: mypy >=1.8.0 ; extra == 'development'
Requires-Dist: pytest >=8.0.0 ; extra == 'development'
Requires-Dist: pytest-cov >=4.1.0 ; extra == 'development'
